gnews/__init__.py
gnews/gnews.py
gnews/utils/__init__.py
gnews/utils/constants.py
gnews/utils/utils.py
Airvue_gn-0.0.3.dist-info/METADATA
Airvue_gn-0.0.3.dist-info/WHEEL
Airvue_gn-0.0.3.dist-info/top_level.txt
Airvue_gn-0.0.3.dist-info/RECORD
