Metadata-Version: 2.1
Name: Airvue-gn
Version: 0.0.3
Summary: Airvue-gn
Home-page: https://github.com/AirvueTech/Airvue-gn
Author: AirvueTech
Author-email: dev@airvue.news
Requires-Dist: feedparser (>=6.0.2)
Requires-Dist: bs4 (>=0.0.1)
Requires-Dist: beautifulsoup4 (>=4.9.3)
Requires-Dist: pymongo (>=3.12.0)
Requires-Dist: dnspython (>=1.16.0)
Requires-Dist: python-dotenv (>=0.19.0)
Requires-Dist: requests (>=2.26.0)
